mermaid/__init__.py
mermaid/config_parser.py
mermaid/custom_optimizers.py
mermaid/custom_pytorch_extensions.py
mermaid/custom_pytorch_extensions_module_version.py
mermaid/data_loader.py
mermaid/data_manager.py
mermaid/data_pool.py
mermaid/data_utils.py
mermaid/data_wrapper.py
mermaid/deep_loss.py
mermaid/deep_networks.py
mermaid/deep_smoothers.py
mermaid/example_generation.py
mermaid/fileio.py
mermaid/finite_differences.py
mermaid/finite_differences_multi_channel.py
mermaid/fixwarnings.py
mermaid/forward_models.py
mermaid/forward_models_wrap.py
mermaid/image_manipulations.py
mermaid/image_sampling.py
mermaid/load_default_settings.py
mermaid/metrics.py
mermaid/model_evaluation.py
mermaid/model_factory.py
mermaid/module_parameters.py
mermaid/multiscale_optimizer.py
mermaid/noisy_convolution.py
mermaid/ode_int.py
mermaid/optimizer_data_loaders.py
mermaid/registration_networks.py
mermaid/regularizer_factory.py
mermaid/res_recorder.py
mermaid/rungekutta_integrators.py
mermaid/similarity_helper_omt.py
mermaid/similarity_measure_factory.py
mermaid/simple_interface.py
mermaid/smoother_factory.py
mermaid/spline_interpolation.py
mermaid/utils.py
mermaid/viewers.py
mermaid/visualize_registration_results.py
mermaid/libraries/__init__.py
mermaid/libraries/functions/__init__.py
mermaid/libraries/functions/map_scale_utils.py
mermaid/libraries/functions/stn_nd.py
mermaid/libraries/modules/__init__.py
mermaid/libraries/modules/asym_conv.py
mermaid/libraries/modules/stn_nd.py
mermaid/torchdiffeq/__init__.py
mermaid/torchdiffeq/_impl/__init__.py
mermaid/torchdiffeq/_impl/adams.py
mermaid/torchdiffeq/_impl/adjoint.py
mermaid/torchdiffeq/_impl/dopri5.py
mermaid/torchdiffeq/_impl/fixed_adams.py
mermaid/torchdiffeq/_impl/fixed_grid.py
mermaid/torchdiffeq/_impl/interp.py
mermaid/torchdiffeq/_impl/misc.py
mermaid/torchdiffeq/_impl/odeint.py
mermaid/torchdiffeq/_impl/rk_common.py
mermaid/torchdiffeq/_impl/solvers.py
mermaid/torchdiffeq/_impl/tsit5.py
mermaid_apps/README.md
mermaid-0.3.2.dist-info/LICENSE
mermaid-0.3.2.dist-info/METADATA
mermaid-0.3.2.dist-info/WHEEL
mermaid-0.3.2.dist-info/top_level.txt
mermaid-0.3.2.dist-info/RECORD
