Metadata-Version: 2.1
Name: mermaid
Version: 0.3.2
Summary: Image registration toolbox based on pyTorch
Home-page: https://github.com/uncbiag/mermaid
Author: Marc Niethammer
Author-email: mn@cs.unc.edu
License: Apache 2.0
Platform: UNKNOWN
Classifier: License :: OSI Approved :: Apache Software License
Classifier: Programming Language :: Python
Classifier: Programming Language :: Python :: 3
Classifier: Programming Language :: Python :: 3.6
Classifier: Environment :: Console
Classifier: Intended Audience :: Developers
Classifier: Programming Language :: Python :: Implementation :: CPython
Classifier: Programming Language :: Python :: Implementation :: PyPy
Requires-Python: >=3.7.0
Requires-Dist: ipython
Requires-Dist: jupyter
Requires-Dist: ipykernel
Requires-Dist: numpy
Requires-Dist: pynrrd
Requires-Dist: future
Requires-Dist: cython
Requires-Dist: scikit-image
Requires-Dist: tabulate
Requires-Dist: termcolor
Requires-Dist: cffi
Requires-Dist: itk
Requires-Dist: torch (>=1.7torchvision)
Requires-Dist: pandas
Requires-Dist: matplotlib
Requires-Dist: scipy
Requires-Dist: openpyxl
Requires-Dist: sphinx-gallery (==0.3.1)
Requires-Dist: sphinx
Requires-Dist: nbsphinx
Requires-Dist: pandoc
Requires-Dist: pypandoc
Requires-Dist: statsmodels
Requires-Dist: progressbar2
